LoadAndSplit/Default_Model.pkl
LoadAndSplit/Load.py
LoadAndSplit/Split.py
LoadAndSplit/__init__.py
LoadAndSplit-1.0.dist-info/METADATA
LoadAndSplit-1.0.dist-info/WHEEL
LoadAndSplit-1.0.dist-info/top_level.txt
LoadAndSplit-1.0.dist-info/RECORD
